{"trial_id": "03", "hyperparameters": {"space": [{"class_name": "Int", "config": {"name": "units_input", "default": null, "conditions": [], "min_value": 64, "max_value": 256, "step": 32, "sampling": "linear"}}, {"class_name": "Float", "config": {"name": "dropout_input", "default": 0.1, "conditions": [], "min_value": 0.1, "max_value": 0.5, "step": 0.1, "sampling": "linear"}}, {"class_name": "Int", "config": {"name": "units_hidden", "default": null, "conditions": [], "min_value": 32, "max_value": 128, "step": 32, "sampling": "linear"}}, {"class_name": "Float", "config": {"name": "dropout_hidden", "default": 0.1, "conditions": [], "min_value": 0.1, "max_value": 0.5, "step": 0.1, "sampling": "linear"}}, {"class_name": "Choice", "config": {"name": "optimizer", "default": "adam", "conditions": [], "values": ["adam", "sgd", "rmsprop"], "ordered": false}}], "values": {"units_input": 192, "dropout_input": 0.4, "units_hidden": 96, "dropout_hidden": 0.1, "optimizer": "adam"}}, "metrics": {"metrics": {"accuracy": {"direction": "max", "observations": [{"value": [0.9189738631248474], "step": 16}]}, "loss": {"direction": "min", "observations": [{"value": [0.2111726775765419], "step": 16}]}, "val_accuracy": {"direction": "max", "observations": [{"value": [0.8797587454319], "step": 16}]}, "val_loss": {"direction": "min", "observations": [{"value": [0.2632463127374649], "step": 16}]}}}, "score": 0.8797587454319, "best_step": 16, "status": "COMPLETED", "message": null}